pyoauthbridge/__init__.py
pyoauthbridge/connect.py
pyoauthbridge/packetDecoder.py
pyoauthbridge/sample.py
pyoauthbridge/server.py
pyoauthbridge/wsclient.py
pyoauthbridge-1.0.20.dist-info/METADATA
pyoauthbridge-1.0.20.dist-info/WHEEL
pyoauthbridge-1.0.20.dist-info/top_level.txt
pyoauthbridge-1.0.20.dist-info/RECORD
