Metadata-Version: 2.1
Name: pyoauthbridge
Version: 1.0.20
Summary: pyoauthbridge is a official python library to communicate with Tradelab API
Home-page: UNKNOWN
Author: Biswajit
Author-email: biswajit@tradelab.com
License: UNKNOWN
Platform: UNKNOWN
